django_extmodels/__init__.py
django_extmodels/manager.py
django_extmodels/models.py
django_extmodels/options.py
django_extmodels/query.py
django_extmodels/settings.py
django_extmodels/utils.py
django_extmodels-0.3.1.dist-info/LICENSE
django_extmodels-0.3.1.dist-info/METADATA
django_extmodels-0.3.1.dist-info/WHEEL
django_extmodels-0.3.1.dist-info/top_level.txt
django_extmodels-0.3.1.dist-info/RECORD
