Metadata-Version: 2.1
Name: django-extmodels
Version: 0.3.1
Summary: Extending the utility of Django Models
Home-page: UNKNOWN
Author: John Bowen
Author-email: jbowen7@gmail.com
License: UNKNOWN
Keywords: django,dynamic,models
Platform: UNKNOWN
Requires-Python: >=3.6
